aneSettings/ConfigSettings.py
aneSettings/CustomLogging.py
aneSettings/Encryption.py
aneSettings/ProjectRoot.py
aneSettings/__about__.py
aneSettings/__init__.py
aneSettings/templates/ConfigSettings.py
aneSettings/templates/__init__.py
anesettings-2025.9.0.dist-info/licenses/LICENSE
anesettings-2025.9.0.dist-info/METADATA
anesettings-2025.9.0.dist-info/WHEEL
anesettings-2025.9.0.dist-info/top_level.txt
anesettings-2025.9.0.dist-info/RECORD
