Metadata-Version: 2.4
Name: aneSettings
Version: 2025.9.0
Summary: High-performance secure core framework for scalable, reliable applications
Author-email: Cybernetic Innovations <github@cyberneticinnovations.com>
Classifier: License :: OSI Approved :: MIT License
Requires-Python: >=3.10
License-File: LICENSE
Requires-Dist: PyYAML~=6.0.2
Requires-Dist: cryptography~=45.0.3
Requires-Dist: loguru~=0.7.3
Requires-Dist: pydantic~=2.11.5
Dynamic: license-file
